deebotozmo/__init__.py
deebotozmo/cli.py
deebotozmo/ecovacs_api.py
deebotozmo/ecovacs_json.py
deebotozmo/ecovacs_mqtt.py
deebotozmo/event_emitter.py
deebotozmo/events.py
deebotozmo/map.py
deebotozmo/models.py
deebotozmo/py.typed
deebotozmo/util.py
deebotozmo/vacuum_bot.py
deebotozmo/commands/__init__.py
deebotozmo/commands/base.py
deebotozmo/commands/battery.py
deebotozmo/commands/charge.py
deebotozmo/commands/charge_state.py
deebotozmo/commands/clean.py
deebotozmo/commands/clean_logs.py
deebotozmo/commands/custom.py
deebotozmo/commands/error.py
deebotozmo/commands/fan_speed.py
deebotozmo/commands/life_span.py
deebotozmo/commands/map.py
deebotozmo/commands/play_sound.py
deebotozmo/commands/relocation.py
deebotozmo/commands/stats.py
deebotozmo/commands/water_info.py
tests/commands/__init__.py
tests/commands/helpers.py
tests/commands/test_fan_speed.py
tests/commands/test_water_info.py
deebotozmo-3.0.2.dist-info/LICENSE.txt
deebotozmo-3.0.2.dist-info/METADATA
deebotozmo-3.0.2.dist-info/WHEEL
deebotozmo-3.0.2.dist-info/entry_points.txt
deebotozmo-3.0.2.dist-info/top_level.txt
deebotozmo-3.0.2.dist-info/RECORD
