Metadata-Version: 2.1
Name: deebotozmo
Version: 3.0.2
Summary: a library for controlling certain deebot vacuums
Home-page: https://github.com/And3rsL/Deebotozmo
Author: Andrea Liosi
Author-email: andrea.liosi@gmail.com
License: GPL-3.0
Keywords: home automation vacuum robot
Platform: UNKNOWN
Classifier: Development Status :: 4 - Beta
Classifier: Intended Audience :: Developers
Classifier: Topic :: Software Development :: Libraries :: Python Modules
Classifier: Topic :: Home Automation
Classifier: License :: OSI Approved :: GNU General Public License v3 (GPLv3)
Classifier: Programming Language :: Python :: 3.8
License-File: LICENSE.txt
Requires-Dist: gmqtt (==0.6.10)
Requires-Dist: numpy (==1.21.2)
Requires-Dist: Pillow (==8.3.2)
Requires-Dist: aiohttp (==3.7.4.post0)
Requires-Dist: click (==8.0.1)
Requires-Dist: cachetools (==4.2.4)
